atmos.py
atmos_rng-1.0.3.dist-info/LICENSE
atmos_rng-1.0.3.dist-info/METADATA
atmos_rng-1.0.3.dist-info/WHEEL
atmos_rng-1.0.3.dist-info/top_level.txt
atmos_rng-1.0.3.dist-info/RECORD
