Metadata-Version: 2.1
Name: atmos-rng
Version: 1.0.3
Summary: A simple random generator based off of atmospheric noise instead of math.
Home-page: https://github.com/therealOri/atmos-rng
Author: therealOri
Author-email: therealOri@duck.com
License: GPL-3.0
License-File: LICENSE
Requires-Dist: requests
